LICENSE
MANIFEST.in
README.md
requirements.txt
setup.cfg
setup.py
src/pyvesync/__init__.py
src/pyvesync/helpers.py
src/pyvesync/vesync.py
src/pyvesync/vesyncbasedevice.py
src/pyvesync/vesyncbulb.py
src/pyvesync/vesyncfan.py
src/pyvesync/vesynckitchen.py
src/pyvesync/vesyncoutlet.py
src/pyvesync/vesyncswitch.py
src/tv4you2016_pyvesync.egg-info/PKG-INFO
src/tv4you2016_pyvesync.egg-info/SOURCES.txt
src/tv4you2016_pyvesync.egg-info/dependency_links.txt
src/tv4you2016_pyvesync.egg-info/requires.txt
src/tv4you2016_pyvesync.egg-info/top_level.txt