Metadata-Version: 2.1
Name: tv4you2016-pyvesync
Version: 0.0.6
Summary: pyvesync is a library to manage Etekcity                 Devices, Cosori Air Fryers and Levoit Air                      Purifiers run on the VeSync app.
Home-page: https://github.com/tv4you2016/pyvesync
Author: Mark Perdue, Joe Trabulsy, Tv4you2016
Author-email: tv4you2016@gmail.com
License: MIT
Keywords: iot,vesync,levoit,etekcity,cosori,valceno
Platform: UNKNOWN
Classifier: License :: OSI Approved :: MIT License
Classifier: Intended Audience :: Developers
Classifier: Intended Audience :: End Users/Desktop
Classifier: Natural Language :: English
Classifier: Programming Language :: Python :: 3.8
Requires-Python: >=3.8
Provides-Extra: dev
License-File: LICENSE
